{
  "schema_version": 3,
  "run_id": 1784449770,
  "created": "2026-07-19T14:29:30",
  "dataset": "gislr",
  "architecture": "gru",
  "model_name": "StreamingGRU",
  "streaming": true,
  "subset": "ME_132",
  "coords": "xy",
  "n_landmarks": 132,
  "feature_dim": 264,
  "n_classes": 250,
  "n_params": 860938,
  "split": {
    "strategy": "stratified 90/10",
    "random_state": 42,
    "n_val": 9448
  },
  "training": {
    "regime": "v2-plateau-300",
    "source": "gislr.1.model.gru.ipynb",
    "epoch_cap": 300,
    "epochs_trained": 85,
    "best_epoch": 70,
    "early_stopped": true,
    "finished": true,
    "wall_time_min": 28.0
  },
  "hyperparameters": {
    "batch_size": 1024,
    "lr": 0.001414,
    "hidden_size": 256,
    "num_layers": 2,
    "dropout": 0.3,
    "weight_decay": 0.0001,
    "epochs": 300,
    "grad_clip": 5.0,
    "lr_factor": 0.5,
    "lr_patience": 5,
    "es_patience": 15,
    "es_min_delta": 0.001,
    "seed": 42,
    "max_seq_len": 128,
    "num_workers": 0,
    "loss": "CE + label smoothing 0.1",
    "precision": "AMP"
  },
  "metrics": {
    "train_val_acc": 0.7495,
    "eval_status": "canonical",
    "overall_accuracy": 0.7492591024555462,
    "macro_accuracy": 0.7473014148981847,
    "median_class_accuracy": 0.7669683257918551,
    "n_classes_below_50pct": 7
  },
  "checkpoints": {
    "best": "best.pt",
    "last": "last.pt"
  },
  "assets": {
    "landmarks": "assets/landmarks.npy",
    "per_class_csv": "assets/per_class_accuracy.csv",
    "per_class_png": "assets/per_class_accuracy.png",
    "eval_summary": "assets/eval_summary.json",
    "val_predictions": "assets/val_predictions.npz"
  },
  "notes": "ME_132 subset \u00b7 regime v2-plateau-300.",
  "submission": {
    "tested": false,
    "platform": null,
    "submitted_at": null,
    "public_score": null,
    "private_score": null,
    "reference": null,
    "notes": ""
  }
}